loo_encoder/encoder.py
loo_encoder/utils.py
loo_encoder-0.0.9.dist-info/METADATA
loo_encoder-0.0.9.dist-info/RECORD
loo_encoder-0.0.9.dist-info/WHEEL
loo_encoder-0.0.9.dist-info/top_level.txt
