Metadata-Version: 2.1
Name: loo-encoder
Version: 0.0.9
Summary: Leave one out encoding of categorical features
Home-page: https://github.com/welfare520/leave-one-out-encoder
Author: He Zhang
Author-email: zhanghe.dr@gmail.com
License: GPL v3
Platform: UNKNOWN
Requires-Dist: pandas
Requires-Dist: numpy
